img_to_webp/__init__.py
img_to_webp/_cli.py
img_to_webp/_config.py
img_to_webp/_exceptions.py
img_to_webp/_image_processor.py
img_to_webp/_main.py
img_to_webp/_models.py
img_to_webp/_resize_strategy.py
img_to_webp-0.1.0.dist-info/licenses/LICENSE
img_to_webp-0.1.0.dist-info/METADATA
img_to_webp-0.1.0.dist-info/WHEEL
img_to_webp-0.1.0.dist-info/entry_points.txt
img_to_webp-0.1.0.dist-info/top_level.txt
img_to_webp-0.1.0.dist-info/RECORD
