Metadata-Version: 2.4
Name: img-to-webp
Version: 0.1.0
Summary: A Python package that provides a command-line interface (CLI) for converting images to the WebP format. It supports various image formats and allows for resizing images based on predefined rules.
Project-URL: Homepage, https://github.com/nipunchamikara/img-to-webp
Project-URL: Issues, https://github.com/nipunchamikara/img-to-webp/issues
Classifier: Development Status :: 3 - Alpha
Classifier: Intended Audience :: Developers
Classifier: License :: OSI Approved :: MIT License
Classifier: Operating System :: OS Independent
Classifier: Programming Language :: Python :: 3
Classifier: Programming Language :: Python :: 3.9
Classifier: Programming Language :: Python :: 3.10
Classifier: Programming Language :: Python :: 3.11
Classifier: Programming Language :: Python :: 3.12
Requires-Python: <4.0,>=3.9
License-File: LICENSE
Requires-Dist: pyyaml<7.0.0,>=6.0.0
Requires-Dist: pillow<12.0.0,>=11.0.0
Dynamic: license-file
